xcdo-0.2.0.dist-info/METADATA
xcdo-0.2.0.dist-info/WHEEL
xcdo-0.2.0.dist-info/entry_points.txt
xcdo-0.2.0.dist-info/licenses/LICENSE
xcdo/__init__.py
xcdo/datatypes.py
xcdo/exceptions.py
xcdo/io_utils.py
xcdo/main.py
xcdo/operators/__init__.py
xcdo/operators/cdo.py
xcdo/operators/info.py
xcdo/operators/mer_stat.py
xcdo/operators/misc.py
xcdo/operators/missing_values.py
xcdo/operators/plotting.py
xcdo/operators/renaming.py
xcdo/operators/selecting.py
xcdo/operators/time_stat.py
xcdo/operators/zon_stat.py
xcdo/registry.py
xcdo/validators.py
xcdo/xarray_accessors.py
xcdo-0.2.0.dist-info/RECORD
