Metadata-Version: 2.1
Name: xcdo
Version: 0.2.0
Author-Email: Prajeesh Ag <prajeeshag@gmail.com>
License: MIT License
Classifier: Programming Language :: Python :: 3
Classifier: Programming Language :: Python :: 3 :: Only
Classifier: Programming Language :: Python :: 3.12
Classifier: Programming Language :: Python :: 3.13
Classifier: Programming Language :: Python :: 3.14
Project-URL: homepage, https://prajeeshag.github.io/xcdo
Project-URL: repository, https://github.com/prajeeshag/xcdo
Project-URL: documentation, https://prajeeshag.github.io/xcdo
Requires-Python: >=3.12
Requires-Dist: cartopy<2.0.0,>=0.24.1
Requires-Dist: cf-xarray<1.0.0,>=0.10.0
Requires-Dist: cfgrib<1.0.0,>=0.9.14.1
Requires-Dist: cftime<2.0.0,>=1.6.4.post1
Requires-Dist: clios>=0.6
Requires-Dist: dask[array,distributed]<2025.0.0,>=2024.11.2
Requires-Dist: eccodes<3.0.0,>=2.39.0
Requires-Dist: nc-time-axis<2.0.0,>=1.4.1
Requires-Dist: netcdf4<2.0.0,>=1.7.2
Requires-Dist: numpy<3.0.0,>=2.1.3
Requires-Dist: xarray<2025.0.0,>=2024.11
Requires-Dist: zarr<3.0.0,>=2.18.3
